virtualenv_make_relocatable-0.0.1.data/scripts/virtualenv-make-relocatable
virtualenv_relocator/__init__.py
virtualenv_relocator/cmd.py
virtualenv_relocator/common.py
virtualenv_relocator/logger.py
virtualenv_relocator/utils.py
virtualenv_make_relocatable-0.0.1.dist-info/METADATA
virtualenv_make_relocatable-0.0.1.dist-info/WHEEL
virtualenv_make_relocatable-0.0.1.dist-info/top_level.txt
virtualenv_make_relocatable-0.0.1.dist-info/RECORD
