Metadata-Version: 2.1
Name: virtualenv-make-relocatable
Version: 0.0.1
Summary: simple tool to make virtualenv provided scripts relocatable
Home-page: https://github.com/heni/virtualenv-make-relocatable
License: UNKNOWN
Platform: UNKNOWN
Classifier: Development Status :: 5 - Production/Stable
Classifier: Environment :: Console
Classifier: Intended Audience :: Developers
Classifier: Operating System :: POSIX :: Linux
Classifier: Operating System :: Microsoft :: Windows
Classifier: License :: OSI Approved :: MIT License
Classifier: Programming Language :: Python :: 3
Classifier: Topic :: Software Development
